{"cameraMode":{"drawMode":0,"name":"Shaded","section":"Shading Mode"},"sceneLighting":true,"audioPlay":false,"sceneViewState":{"m_AlwaysRefresh":false,"showFog":true,"showSkybox":true,"showFlares":true,"showImageEffects":true,"showParticleSystems":true,"showVisualEffectGraphs":true,"m_FxEnabled":true},"in2DMode":false,"pivot":{"x":7.878993988037109,"y":0.7115283012390137,"z":-3.621701955795288},"rotation":{"x":-0.10387423634529114,"y":-0.36260056495666506,"z":0.041030656546354297,"w":-0.9253863096237183},"size":0.9484807848930359,"orthographic":false}